README.rst
setup.py
bin/wtf
pywtf/__init__.py
pywtf/wtf.py
pywtf.egg-info/PKG-INFO
pywtf.egg-info/SOURCES.txt
pywtf.egg-info/dependency_links.txt
pywtf.egg-info/top_level.txt