Metadata-Version: 1.1
Name: pywtf
Version: 0.0.3
Summary: Command to get overview of linux system state
Home-page: http://github.com/lorien/wtf
Author: Gregory Petukhov
Author-email: lorien@lorien.name
License: MIT
Keywords: linux system usage load
Platform: UNKNOWN
Classifier: Programming Language :: Python
Classifier: Programming Language :: Python :: 3.4
Classifier: License :: OSI Approved :: MIT License
Classifier: Development Status :: 5 - Production/Stable
Classifier: Environment :: Console
Classifier: Intended Audience :: Developers
Classifier: Operating System :: OS Independent
Classifier: Topic :: Software Development :: Libraries :: Python Modules
Classifier: Topic :: Utilities
